LICENSE
MANIFEST.in
README.md
setup.py
pingdatautil/AWSStorage.py
pingdatautil/AzureStorage.py
pingdatautil/DataConnection.py
pingdatautil/DataExport.py
pingdatautil/EngineHelper.py
pingdatautil/ExcelFormatter.py
pingdatautil/ExcelReader.py
pingdatautil/GoogleDrive.py
pingdatautil/GoogleSheet.py
pingdatautil/GoogleStorage.py
pingdatautil/HyperClass.py
pingdatautil/JDBCExport.py
pingdatautil/JDBCHelper.py
pingdatautil/LineNotify.py
pingdatautil/Logger.py
pingdatautil/ODBCExport.py
pingdatautil/ODBCHelper.py
pingdatautil/ODBCUtil.py
pingdatautil/UnitTest.py
pingdatautil/_Util.py
pingdatautil/__init__.py
pingdatautil.egg-info/PKG-INFO
pingdatautil.egg-info/SOURCES.txt
pingdatautil.egg-info/dependency_links.txt
pingdatautil.egg-info/requires.txt
pingdatautil.egg-info/top_level.txt