Metadata-Version: 2.1
Name: pingdatautil
Version: 0.0.5
Summary: Ping's Data Utility Package
Author: Vorapol Ping
License-File: LICENSE
